askpass/__init__.py
askpass/__version__.py
askpass/_logging.py
askpass/askpass.py
askpass/pinentry.py
askpass-0.1.data/data/LICENSE.txt
askpass-0.1.data/data/requirements.txt
askpass-0.1.dist-info/LICENSE.txt
askpass-0.1.dist-info/METADATA
askpass-0.1.dist-info/WHEEL
askpass-0.1.dist-info/entry_points.txt
askpass-0.1.dist-info/top_level.txt
askpass-0.1.dist-info/RECORD
