Metadata-Version: 2.1
Name: askpass
Version: 0.1
Summary: Wrapper for the pinentry program
Home-page: https://framagit.org/1ohmatr/sw/py/askpass.git
Author: neze
Author-email: neze@melix.org
License: UNKNOWN
Platform: UNKNOWN
Classifier: Programming Language :: Python :: 3
Classifier: License :: OSI Approved :: MIT License
Requires-Dist: pathlib2
